QuizEngine4Trivia/__init__.py
QuizEngine4Trivia/main.py
QuizEngine4Trivia/Models/__init__.py
QuizEngine4Trivia/Models/question_model.py
QuizEngine4Trivia/Models/trivia_api_model.py
QuizEngine4Trivia/Models/trivia_data_model.py
tirsvadCLI_quiz_engine_4_trivia-0.0.4.dist-info/LICENSE
tirsvadCLI_quiz_engine_4_trivia-0.0.4.dist-info/METADATA
tirsvadCLI_quiz_engine_4_trivia-0.0.4.dist-info/WHEEL
tirsvadCLI_quiz_engine_4_trivia-0.0.4.dist-info/top_level.txt
tirsvadCLI_quiz_engine_4_trivia-0.0.4.dist-info/RECORD
