Metadata-Version: 2.1
Name: tirsvadCLI-quiz-engine-4-trivia
Version: 0.0.4
Home-page: https://github.com/TirsvadCLI
Download-URL: https://github.com/TirsvadCLI/Python.QuizEngine4Trivia/releases/download/v0.0.1a2/tirsvadcli_quiz_engine_4_trivia-0.0.1a2.tar.gz
Author: Jens Tirsvad Nielsen
Author-email: jenstirsvad@gmail.com
Classifier: License :: OSI Approved :: GNU Affero General Public License v3 or later (AGPLv3+)
Classifier: Programming Language :: Python :: 3
Classifier: Programming Language :: Python :: 3.10
Classifier: Programming Language :: Python :: 3.11
Classifier: Environment :: Console
Classifier: Operating System :: POSIX :: Linux
Classifier: Topic :: Software Development :: Libraries :: Python Modules
Requires-Python: >=3.10
License-File: LICENSE
Requires-Dist: requests
